ninja_aio/__init__.py
ninja_aio/api.py
ninja_aio/auth.py
ninja_aio/exceptions.py
ninja_aio/parsers.py
ninja_aio/renders.py
ninja_aio/types.py
ninja_aio/decorators/__init__.py
ninja_aio/decorators/operations.py
ninja_aio/decorators/views.py
ninja_aio/factory/__init__.py
ninja_aio/factory/operations.py
ninja_aio/helpers/__init__.py
ninja_aio/helpers/api.py
ninja_aio/helpers/query.py
ninja_aio/models/__init__.py
ninja_aio/models/serializers.py
ninja_aio/models/utils.py
ninja_aio/schemas/__init__.py
ninja_aio/schemas/api.py
ninja_aio/schemas/filters.py
ninja_aio/schemas/generics.py
ninja_aio/schemas/helpers.py
ninja_aio/views/__init__.py
ninja_aio/views/api.py
ninja_aio/views/mixins.py
django_ninja_aio_crud-2.18.1.dist-info/licenses/LICENSE
django_ninja_aio_crud-2.18.1.dist-info/WHEEL
django_ninja_aio_crud-2.18.1.dist-info/METADATA
django_ninja_aio_crud-2.18.1.dist-info/RECORD
