Metadata-Version: 2.4
Name: django-ninja-aio-crud
Version: 2.18.1
Summary: Django Ninja AIO CRUD - Rest Framework
Author: Giuseppe Casillo
Requires-Python: >=3.10, <3.15
Classifier: Operating System :: OS Independent
Classifier: Topic :: Internet
Classifier: Topic :: Software Development :: Libraries :: Application Frameworks
Classifier: Topic :: Software Development :: Libraries :: Python Modules
Classifier: Topic :: Software Development :: Libraries
Classifier: Topic :: Software Development
Classifier: Environment :: Web Environment
Classifier: Intended Audience :: Developers
Classifier: License :: OSI Approved :: MIT License
Classifier: Programming Language :: Python :: 3.10
Classifier: Programming Language :: Python :: 3.11
Classifier: Programming Language :: Python :: 3.12
Classifier: Programming Language :: Python :: 3.13
Classifier: Programming Language :: Python :: 3.14
Classifier: Programming Language :: Python :: 3 :: Only
Classifier: Framework :: Django
Classifier: Framework :: AsyncIO
Classifier: Topic :: Internet :: WWW/HTTP :: HTTP Servers
Classifier: Topic :: Internet :: WWW/HTTP
License-File: LICENSE
Requires-Dist: django-ninja >=1.3.0, <1.6
Requires-Dist: joserfc >=1.0.0, <= 1.4.1
Requires-Dist: orjson >= 3.10.7, <= 3.11.5
Requires-Dist: coverage ; extra == "test"
Project-URL: Documentation, https://django-ninja-aio.com
Project-URL: Repository, https://github.com/caspel26/django-ninja-aio-crud
Provides-Extra: test
